test_for_pyscaffold/__init__.py
test_for_pyscaffold/sayyes.py
test_for_pyscaffold/skeleton.py
test_for_pyscaffold/test_for_pyscaffold.py
test_for_pyscaffold-0.0.3.dist-info/DESCRIPTION.rst
test_for_pyscaffold-0.0.3.dist-info/METADATA
test_for_pyscaffold-0.0.3.dist-info/RECORD
test_for_pyscaffold-0.0.3.dist-info/WHEEL
test_for_pyscaffold-0.0.3.dist-info/metadata.json
test_for_pyscaffold-0.0.3.dist-info/top_level.txt
