Metadata-Version: 2.0
Name: test-for-pyscaffold
Version: 0.0.3
Summary: Add a short description here!
Home-page: http://...
Author: wangpenghui
Author-email: wangpenghui@gene.ac
License: none
Platform: UNKNOWN
Classifier: Development Status :: 4 - Beta
Classifier: Programming Language :: Python
